_qoa.pyd
qoa/__init__.py
qoa/ffi_builder.py
qoa-0.1.0.dist-info/LICENSE
qoa-0.1.0.dist-info/METADATA
qoa-0.1.0.dist-info/WHEEL
qoa-0.1.0.dist-info/top_level.txt
qoa-0.1.0.dist-info/RECORD
