Metadata-Version: 2.1
Name: qoa
Version: 0.1.0
Summary: A library for reading and writing QOA files
Home-page: https://github.com/HaxelWorks/qoa-python
Author: Axel Roijers
Author-email: haxelworks@gmail.com
License: MIT
Classifier: Development Status :: 3 - Alpha
Classifier: Programming Language :: Python :: 3
Classifier: Topic :: File Formats
Classifier: Topic :: Multimedia :: Sound/Audio :: Conversion
Classifier: Topic :: System :: Archiving :: Compression
Classifier: License :: OSI Approved :: MIT License
License-File: LICENSE
Requires-Dist: cffi >=1.16.0
Requires-Dist: numpy >=1.26.0
